{"links": [{"source": "ARAGORN", "target": "FRODO", "value": 6}, {"source": "ARAGORN", "target": "GANDALF", "value": 3}, {"source": "ARAGORN", "target": "RING", "value": 3}, {"source": "ARAGORN", "target": "SAM", "value": 2}, {"source": "ARAGORN", "target": "BOROMIR", "value": 2}, {"source": "ARAGORN", "target": "SAURON", "value": 2}, {"source": "ARAGORN", "target": "HALDIR", "value": 1}, {"source": "ARAGORN", "target": "LEGOLAS", "value": 1}, {"source": "ARAGORN", "target": "ELROND", "value": 1}, {"source": "ARWEN", "target": "FRODO", "value": 3}, {"source": "ARWEN", "target": "ARAGORN", "value": 1}, {"source": "ARWEN", "target": "ARWEN", "value": 1}, {"source": "BARLIMAN", "target": "GANDALF", "value": 2}, {"source": "BILBO", "target": "GANDALF", "value": 6}, {"source": "BILBO", "target": "FRODO", "value": 5}, {"source": "BILBO", "target": "RING", "value": 2}, {"source": "BILBO", "target": "BILBO", "value": 1}, {"source": "BOROMIR", "target": "RING", "value": 2}, {"source": "BOROMIR", "target": "ARAGORN", "value": 1}, {"source": "BOROMIR", "target": "SAURON", "value": 1}, {"source": "BOROMIR", "target": "LEGOLAS", "value": 1}, {"source": "ELROND", "target": "RING", "value": 4}, {"source": "ELROND", "target": "FRODO", "value": 1}, {"source": "ELROND", "target": "BOROMIR", "value": 1}, {"source": "ELROND", "target": "GIMLI", "value": 1}, {"source": "FRODO", "target": "SAM", "value": 7}, {"source": "FRODO", "target": "BILBO", "value": 6}, {"source": "FRODO", "target": "GANDALF", "value": 5}, {"source": "FRODO", "target": "ROSIE", "value": 2}, {"source": "FRODO", "target": "GAFFER", "value": 1}, {"source": "FRODO", "target": "GOLLUM", "value": 1}, {"source": "FRODO", "target": "RING", "value": 1}, {"source": "FRODO", "target": "PIPPIN", "value": 1}, {"source": "GAFFER", "target": "FRODO", "value": 1}, {"source": "GALADRIEL", "target": "RING", "value": 13}, {"source": "GALADRIEL", "target": "GOLLUM", "value": 3}, {"source": "GALADRIEL", "target": "FRODO", "value": 2}, {"source": "GALADRIEL", "target": "SAURON", "value": 2}, {"source": "GALADRIEL", "target": "BILBO", "value": 1}, {"source": "GANDALF", "target": "FRODO", "value": 7}, {"source": "GANDALF", "target": "RING", "value": 6}, {"source": "GANDALF", "target": "BILBO", "value": 4}, {"source": "GANDALF", "target": "GIMLI", "value": 3}, {"source": "GANDALF", "target": "SARUMAN", "value": 2}, {"source": "GANDALF", "target": "GOLLUM", "value": 2}, {"source": "GANDALF", "target": "ELROND", "value": 1}, {"source": "GANDALF", "target": "ARAGORN", "value": 1}, {"source": "GIMLI", "target": "GANDALF", "value": 1}, {"source": "GIMLI", "target": "RING", "value": 1}, {"source": "HALDIR", "target": "ARAGORN", "value": 2}, {"source": "HALDIR", "target": "LEGOLAS", "value": 1}, {"source": "LEGOLAS", "target": "HALDIR", "value": 1}, {"source": "LEGOLAS", "target": "ELROND", "value": 1}, {"source": "LEGOLAS", "target": "RING", "value": 1}, {"source": "MERRY", "target": "PIPPIN", "value": 5}, {"source": "MERRY", "target": "FRODO", "value": 5}, {"source": "MERRY", "target": "SAM", "value": 2}, {"source": "MERRY", "target": "ARAGORN", "value": 1}, {"source": "MERRY", "target": "GANDALF", "value": 1}, {"source": "PIPPIN", "target": "FRODO", "value": 7}, {"source": "PIPPIN", "target": "MERRY", "value": 3}, {"source": "SAM", "target": "FRODO", "value": 11}, {"source": "SAM", "target": "GANDALF", "value": 1}, {"source": "SANDYMAN", "target": "BILBO", "value": 1}, {"source": "SARUMAN", "target": "SAURON", "value": 1}, {"source": "SARUMAN", "target": "GANDALF", "value": 1}], "nodes": [{"id": "ARAGORN", "race": "Men"}, {"id": "ARWEN", "race": "Half-elven,Men"}, {"id": "BARLIMAN", "race": "Men"}, {"id": "BILBO", "race": "Hobbit"}, {"id": "BOROMIR", "race": "Men"}, {"id": "ELROND", "race": "Half-elven"}, {"id": "FRODO", "race": "Hobbit"}, {"id": "GAFFER", "race": "Hobbit"}, {"id": "GALADRIEL", "race": "Elf"}, {"id": "GANDALF", "race": "Maiar"}, {"id": "GIMLI", "race": "Dwarf"}, {"id": "GOLLUM", "race": "Hobbit"}, {"id": "HALDIR", "race": "Elf"}, {"id": "LEGOLAS", "race": "Elf"}, {"id": "MERRY", "race": "Hobbit"}, {"id": "PIPPIN", "race": "Hobbit"}, {"id": "RING", "race": "Vampire"}, {"id": "ROSIE", "race": "Hobbit"}, {"id": "SAM", "race": "Hobbit"}, {"id": "SANDYMAN", "race": "Hobbit"}, {"id": "SARUMAN", "race": "Maiar"}, {"id": "SAURON", "race": "Maiar"}]}